justsdk/__init__.py
justsdk/ansi.py
justsdk/color_print.py
justsdk/file_utils.py
justsdk/py.typed
justsdk-2.4.1.dist-info/METADATA
justsdk-2.4.1.dist-info/WHEEL
justsdk-2.4.1.dist-info/entry_points.txt
justsdk-2.4.1.dist-info/RECORD
