Metadata-Version: 2.4
Name: justsdk
Version: 2.4.1
Summary: Just a lightweight development kit.
Project-URL: Repository, https://github.com/eesuhn/justsdk
Author-email: eesuhn <eason.yihong@gmail.com>
Requires-Python: >=3.11
Requires-Dist: orjson>=3.10.18
Requires-Dist: pygments>=2.19.2
Requires-Dist: pyyaml>=6.0.2
